tsip/__init__.py
tsip/config.py
tsip/hlapi.py
tsip/llapi.py
tsip/structs.py
tsip-0.3.2.dist-info/DESCRIPTION.rst
tsip-0.3.2.dist-info/METADATA
tsip-0.3.2.dist-info/RECORD
tsip-0.3.2.dist-info/WHEEL
tsip-0.3.2.dist-info/metadata.json
tsip-0.3.2.dist-info/top_level.txt
