Metadata-Version: 2.0
Name: tsip
Version: 0.3.2
Summary: Python package for parsing and creating TSIP packets
Home-page: https://github.com/mjuenema/python-TSIP
Author: Markus Juenemann
Author-email: markus@juenemann.net
License: BSD License
Keywords: TSIP,Trimble,GPS
Platform: UNKNOWN
Classifier: Development Status :: 4 - Beta
Classifier: Intended Audience :: Developers
Classifier: License :: OSI Approved :: BSD License
Classifier: Natural Language :: English
Classifier: Topic :: Software Development :: Libraries
Classifier: Topic :: System :: Hardware
Classifier: Programming Language :: Python :: 2.6
Classifier: Programming Language :: Python :: 2.7
Classifier: Programming Language :: Python :: 3.3
Classifier: Programming Language :: Python :: 3.4
Classifier: Programming Language :: Python :: 3.5
Classifier: Programming Language :: Python :: 3.6
Classifier: Programming Language :: Python :: Implementation :: PyPy
